MANIFEST.in
README.md
setup.py
pyCEDFS/CFS64.dll
pyCEDFS/CFSConverter.py
pyCEDFS/__init__.py
pyCEDFS/pyCEDFS.py
pyCEDFS.egg-info/PKG-INFO
pyCEDFS.egg-info/SOURCES.txt
pyCEDFS.egg-info/dependency_links.txt
pyCEDFS.egg-info/requires.txt
pyCEDFS.egg-info/top_level.txt
pyCEDFS/.ipynb_checkpoints/pyCEDFS-checkpoint.py
pyCEDFS/lib/CFS32.dll
pyCEDFS/lib/CFS64.dll
pyCEDFS/lib/__init__.py
pyCEDFS/tests/iotest.py
pyCEDFS/tests/nwbconverttest.py