Metadata-Version: 2.1
Name: pyCEDFS
Version: 0.1.6.3
Summary: A python package to read data from CFS files generated by the signal software from CED systems
Home-page: https://github.com/smestern
Author: Smestern
Author-email: smestern@gmail.com
License: MIT License
Platform: https://github.com/smestern
Classifier: Development Status :: 3 - Alpha
Classifier: Intended Audience :: Developers
Classifier: Topic :: Software Development 
Classifier: License :: OSI Approved :: MIT License
Classifier: Programming Language :: Python :: 3
Classifier: Programming Language :: Python :: 3.4
Classifier: Programming Language :: Python :: 3.5
Classifier: Programming Language :: Python :: 3.6
